{
    "features":[
        {
    "geometry": {
    "coordinates": [
    [
    [
    
    -77.0566,
    -12.035900900900902
    ],
    [
    
    -77.0566,
    -12.035
    ],
    [

    -77.0566,
    -12.035
    ],
    [

    -77.05569909909912,
    -12.035900900900902
    ],
    [

    -77.0566,
    -12.035900900900902
    ]
    ]
    ],
    "type": "Polygon"
    },
    "id": "00_00",
    "properties": {
    "name": "00_00",
    "pollution": 0
    },
    "type": "Feature"
    },
    {
    "geometry": {
    "coordinates": [
    [
    [

    -77.0556990990991,
    -12.035900900900902
    ],
    [

    -77.0556990990991,
    -12.035
    ],
    [
    
    -77.0556990990991,
    -12.035
    ],
    [
    
    -77.05479819819821,
    -12.035900900900902
    ],
    [
    
    -77.0556990990991,
    -12.035900900900902
    ]
    ]
    ],
    "type": "Polygon"
    },
    "id": "00_01",
    "properties": {
    "name": "00_01",
    "pollution": 0
    },
    "type": "Feature"
    }
    ],
    "type":"FeatureCollection",
    "timestamp":"2021-06-07"
}